.svnignore
README.txt
URLS.txt
dev.cfg
import-photos.py
sample-prod.cfg
setup.py
start-engal.py
engal/__init__.py
engal/controllers.py
engal/findcontroller.py
engal/gallerycontroller.py
engal/identitymodel.py
engal/json.py
engal/model.py
engal/release.py
engal/resourcecontroller.py
engal/tagcontroller.py
engal/util.py
engal.egg-info/PKG-INFO
engal.egg-info/SOURCES.txt
engal.egg-info/dependency_links.txt
engal.egg-info/not-zip-safe
engal.egg-info/paster_plugins.txt
engal.egg-info/requires.txt
engal.egg-info/sqlobject.txt
engal.egg-info/top_level.txt
engal/config/__init__.py
engal/config/app.cfg
engal/config/log.cfg
engal/ibox/__init__.py
engal/ibox/release.py
engal/ibox/widgets.py
engal/ibox/static/css/ibox.css
engal/ibox/static/images/indicator.gif
engal/ibox/static/javascript/ibox.js
engal/ibox/templates/__init__.py
engal/static/css/engal.css
engal/static/images/engal.png
engal/static/images/favicon.ico
engal/static/images/tg_under_the_hood.png
engal/templates/__init__.py
engal/templates/findaspect.kid
engal/templates/findtag.kid
engal/templates/findwelcome.kid
engal/templates/firstuser.kid
engal/templates/frontpage.kid
engal/templates/gallery_frontpage.kid
engal/templates/login.kid
engal/templates/master.kid
engal/templates/photo.kid
engal/templates/photosets.kid
engal/templates/standardform.kid
engal/templates/tag.kid
engal/templates/tagaspect.kid
engal/templates/tagwelcome.kid
engal/templates/userpage.kid
engal/templates/welcome.kid
engal/tests/__init__.py
engal/tests/test_controllers.py
engal/tests/test_model.py
tagicons/default.png
