Metadata-Version: 1.0
Name: engal
Version: 0.3.1
Summary: Simple photo gallery
Home-page: http://mithrandr.moria.org/code/engal/
Author: Neil Blakey-Milner
Author-email: nbm@mithrandr.moria.org
License: MIT
Download-URL: http://mithrandr.moria.org/code/engal/
Keywords: turbogears.app
Platform: UNKNOWN
Classifier: Development Status :: 3 - Alpha
Classifier: Operating System :: OS Independent
Classifier: Programming Language :: Python
Classifier: Topic :: Software Development :: Libraries :: Python Modules
Classifier: Framework :: TurboGears
Classifier: Framework :: TurboGears :: Applications
